{"nodes": [{"id": "n_plan_md", "label": "SFFS master build plan: phases, checkpoints, directory layout, dependency matrix", "file_type": "document", "source_file": "SFFS/plan.md", "source_location": null, "source_url": null, "captured_at": null, "author": null, "contributor": null}], "edges": [{"source": "n_plan_md", "target": "c_aes256_gcm", "relation": "references", "confidence": "EXTRACTED", "source_file": "SFFS/plan.md", "source_location": null, "weight": 1.0}, {"source": "n_plan_md", "target": "c_rsa_oaep_wrap", "relation": "references", "confidence": "EXTRACTED", "source_file": "SFFS/plan.md", "source_location": null, "weight": 1.0}, {"source": "n_plan_md", "target": "c_sha256_integrity", "relation": "references", "confidence": "EXTRACTED", "source_file": "SFFS/plan.md", "source_location": null, "weight": 1.0}, {"source": "n_plan_md", "target": "c_argon2id_auth", "relation": "references", "confidence": "EXTRACTED", "source_file": "SFFS/plan.md", "source_location": null, "weight": 1.0}, {"source": "n_plan_md", "target": "c_cloud_gdrive", "relation": "references", "confidence": "EXTRACTED", "source_file": "SFFS/plan.md", "source_location": null, "weight": 1.0}], "hyperedges": []}